{
  "type": "GepPromptArtifact",
  "at": "2026-02-13T05:17:23.380Z",
  "cycle_id": "Cycle #0007",
  "run_id": "run_1770959843365",
  "prompt_path": "/home/nosyt/.openclaw/workspace/skills/capability-evolver/memory/gep_prompt_Cycle_#0007_run_1770959843365.txt",
  "meta": {
    "agent": "main",
    "drift_enabled": false,
    "review_mode": false,
    "dry_run": false,
    "mutation_id": "mut_1770959843363",
    "personality_key": "rigor=0.7|creativity=0.3|verbosity=0.3|risk_tolerance=0.4|obedience=0.9"
  }
}
